claudebridge
dist
screenshots
styles
