Metadata-Version: 2.4
Name: claudeprobridge
Version: 0.1.0
Summary: OpenAI-compatible API bridge for Claude using OAuth tokens
Author: Ylan Allouche
License-Expression: MIT
Requires-Python: >=3.10
License-File: LICENSE
Requires-Dist: flask>=3.0.0
Requires-Dist: python-dotenv>=1.0.0
Requires-Dist: requests>=2.31.0
Requires-Dist: loguru>=0.7.3
Requires-Dist: waitress>=3.0.0
Requires-Dist: pyhtml-htmx>=0.1
Requires-Dist: pyhtml-cem>=0.1
Dynamic: license-file
